fxiqoption/__init__.py
fxiqoption/api.py
fxiqoption/connection_error.py
fxiqoption/constants.py
fxiqoption/country_id.py
fxiqoption/easyapi.py
fxiqoption/expiration.py
fxiqoption/global_value.py
fxiqoption/stable_api.py
fxiqoption/http/__init__.py
fxiqoption/http/appinit.py
fxiqoption/http/auth.py
fxiqoption/http/billing.py
fxiqoption/http/buyback.py
fxiqoption/http/changebalance.py
fxiqoption/http/events.py
fxiqoption/http/getprofile.py
fxiqoption/http/getregdata.py
fxiqoption/http/login.py
fxiqoption/http/loginv2.py
fxiqoption/http/logout.py
fxiqoption/http/profile.py
fxiqoption/http/register.py
fxiqoption/http/resource.py
fxiqoption/http/token.py
fxiqoption/ws/__init__.py
fxiqoption/ws/client.py
fxiqoption/ws/chanels/__init__.py
fxiqoption/ws/chanels/api_game_betinfo.py
fxiqoption/ws/chanels/api_game_getoptions.py
fxiqoption/ws/chanels/base.py
fxiqoption/ws/chanels/buy_place_order_temp.py
fxiqoption/ws/chanels/buyback.py
fxiqoption/ws/chanels/buyv2.py
fxiqoption/ws/chanels/buyv3.py
fxiqoption/ws/chanels/cancel_order.py
fxiqoption/ws/chanels/candles.py
fxiqoption/ws/chanels/change_auto_margin_call.py
fxiqoption/ws/chanels/change_tpsl.py
fxiqoption/ws/chanels/changebalance.py
fxiqoption/ws/chanels/close_position.py
fxiqoption/ws/chanels/digital_option.py
fxiqoption/ws/chanels/get_available_leverages.py
fxiqoption/ws/chanels/get_balances.py
fxiqoption/ws/chanels/get_deferred_orders.py
fxiqoption/ws/chanels/get_financial_information.py
fxiqoption/ws/chanels/get_order.py
fxiqoption/ws/chanels/get_overnight_fee.py
fxiqoption/ws/chanels/get_positions.py
fxiqoption/ws/chanels/heartbeat.py
fxiqoption/ws/chanels/instruments.py
fxiqoption/ws/chanels/leaderboard.py
fxiqoption/ws/chanels/sell_option.py
fxiqoption/ws/chanels/setactives.py
fxiqoption/ws/chanels/ssid.py
fxiqoption/ws/chanels/strike_list.py
fxiqoption/ws/chanels/subscribe.py
fxiqoption/ws/chanels/traders_mood.py
fxiqoption/ws/chanels/unsubscribe.py
fxiqoption/ws/chanels/user.py
fxiqoption/ws/objects/__init__.py
fx_iqoption-1.0.16.dist-info/METADATA
fx_iqoption-1.0.16.dist-info/WHEEL
fx_iqoption-1.0.16.dist-info/top_level.txt
fx_iqoption-1.0.16.dist-info/RECORD
