Metadata-Version: 2.4
Name: fx-iqoption
Version: 1.0.16
Summary: IQ Option API wrapper for Python
Home-page: https://github.com/fxneiram/fx-iqoption
Author: Faver Xavier Neira Molina
Author-email: fxneiram@gmail.com
Requires-Dist: pylint
Requires-Dist: requests
Requires-Dist: websocket-client>=0.56
Dynamic: author
Dynamic: author-email
Dynamic: description
Dynamic: home-page
Dynamic: requires-dist
Dynamic: summary
